[
    {
        "name": "id",
        "dbType": "bigInteger,true,true",
        "htmlType": "number",
        "validations": "",
        "searchable": false,
        "fillable": false,
        "primary": true,
        "inForm": false,
        "inIndex": false,
        "inView": false
    },
    {
        "name": "issuable_type",
        "dbType": "string",
        "htmlType": "text",
        "validations": "",
        "searchable": true,
        "fillable": true,
        "primary": false,
        "inForm": true,
        "inIndex": true,
        "inView": true
    },
    {
        "name": "issuable_id",
        "dbType": "bigInteger,false,true",
        "htmlType": "number",
        "validations": "",
        "searchable": true,
        "fillable": true,
        "primary": false,
        "inForm": true,
        "inIndex": true,
        "inView": true
    },
    {
        "name": "whereable_type",
        "dbType": "string",
        "htmlType": "text",
        "validations": "",
        "searchable": true,
        "fillable": true,
        "primary": false,
        "inForm": true,
        "inIndex": true,
        "inView": true
    },
    {
        "name": "whereable_id",
        "dbType": "bigInteger,false,true",
        "htmlType": "number",
        "validations": "",
        "searchable": true,
        "fillable": true,
        "primary": false,
        "inForm": true,
        "inIndex": true,
        "inView": true
    },
    {
        "name": "issuer_type",
        "dbType": "string",
        "htmlType": "text",
        "validations": "",
        "searchable": true,
        "fillable": true,
        "primary": false,
        "inForm": true,
        "inIndex": true,
        "inView": true
    },
    {
        "name": "issuer_id",
        "dbType": "bigInteger,false,true",
        "htmlType": "number",
        "validations": "",
        "searchable": true,
        "fillable": true,
        "primary": false,
        "inForm": true,
        "inIndex": true,
        "inView": true
    },
    {
        "name": "recipient_type",
        "dbType": "string",
        "htmlType": "text",
        "validations": "",
        "searchable": true,
        "fillable": true,
        "primary": false,
        "inForm": true,
        "inIndex": true,
        "inView": true
    },
    {
        "name": "recipient_id",
        "dbType": "bigInteger,false,true",
        "htmlType": "number",
        "validations": "",
        "searchable": true,
        "fillable": true,
        "primary": false,
        "inForm": true,
        "inIndex": true,
        "inView": true
    },
    {
        "name": "signator_id",
        "dbType": "bigInteger,false,true",
        "htmlType": "number",
        "validations": "",
        "searchable": true,
        "fillable": true,
        "primary": false,
        "inForm": true,
        "inIndex": true,
        "inView": true
    },
    {
        "name": "custom_name",
        "dbType": "string",
        "htmlType": "text",
        "validations": "",
        "searchable": true,
        "fillable": true,
        "primary": false,
        "inForm": true,
        "inIndex": true,
        "inView": true
    },
    {
        "name": "rank",
        "dbType": "integer,false,true",
        "htmlType": "number",
        "validations": "",
        "searchable": true,
        "fillable": true,
        "primary": false,
        "inForm": true,
        "inIndex": true,
        "inView": true
    },
    {
        "name": "parent_id",
        "dbType": "bigInteger,false,true",
        "htmlType": "number",
        "validations": "",
        "searchable": true,
        "fillable": true,
        "primary": false,
        "inForm": true,
        "inIndex": true,
        "inView": true
    },
    {
        "name": "issued_on",
        "dbType": "date",
        "htmlType": "date",
        "validations": "",
        "searchable": true,
        "fillable": true,
        "primary": false,
        "inForm": true,
        "inIndex": true,
        "inView": true
    },
    {
        "name": "reason",
        "dbType": "string",
        "htmlType": "text",
        "validations": "",
        "searchable": true,
        "fillable": true,
        "primary": false,
        "inForm": true,
        "inIndex": true,
        "inView": true
    },
    {
        "name": "image",
        "dbType": "string",
        "htmlType": "text",
        "validations": "",
        "searchable": true,
        "fillable": true,
        "primary": false,
        "inForm": true,
        "inIndex": true,
        "inView": true
    },
    {
        "name": "revoked_by",
        "dbType": "bigInteger,false,true",
        "htmlType": "number",
        "validations": "",
        "searchable": true,
        "fillable": true,
        "primary": false,
        "inForm": true,
        "inIndex": true,
        "inView": true
    },
    {
        "name": "revoked_on",
        "dbType": "date",
        "htmlType": "date",
        "validations": "",
        "searchable": true,
        "fillable": true,
        "primary": false,
        "inForm": true,
        "inIndex": true,
        "inView": true
    },
    {
        "name": "revocation",
        "dbType": "string",
        "htmlType": "text",
        "validations": "",
        "searchable": true,
        "fillable": true,
        "primary": false,
        "inForm": true,
        "inIndex": true,
        "inView": true
    },
    {
        "name": "created_by",
        "dbType": "bigInteger,false,true",
        "htmlType": "number",
        "validations": "",
        "searchable": true,
        "fillable": true,
        "primary": false,
        "inForm": true,
        "inIndex": true,
        "inView": true
    },
    {
        "name": "created_at",
        "dbType": "datetime",
        "htmlType": "date",
        "validations": "",
        "searchable": false,
        "fillable": false,
        "primary": false,
        "inForm": false,
        "inIndex": false,
        "inView": false
    },
    {
        "name": "updated_by",
        "dbType": "bigInteger,false,true",
        "htmlType": "number",
        "validations": "",
        "searchable": true,
        "fillable": true,
        "primary": false,
        "inForm": true,
        "inIndex": true,
        "inView": true
    },
    {
        "name": "updated_at",
        "dbType": "datetime",
        "htmlType": "date",
        "validations": "",
        "searchable": false,
        "fillable": false,
        "primary": false,
        "inForm": false,
        "inIndex": false,
        "inView": false
    },
    {
        "name": "deleted_by",
        "dbType": "bigInteger,false,true",
        "htmlType": "number",
        "validations": "",
        "searchable": true,
        "fillable": true,
        "primary": false,
        "inForm": true,
        "inIndex": true,
        "inView": true
    },
    {
        "name": "deleted_at",
        "dbType": "datetime",
        "htmlType": "date",
        "validations": "",
        "searchable": false,
        "fillable": false,
        "primary": false,
        "inForm": false,
        "inIndex": false,
        "inView": false
    },
    {
        "type": "relation",
        "relation": "mt1,User,created_by"
    },
    {
        "type": "relation",
        "relation": "mt1,User,deleted_by"
    },
    {
        "type": "relation",
        "relation": "mt1,Persona,revoked_by"
    },
    {
        "type": "relation",
        "relation": "mt1,Persona,signator_id"
    },
    {
        "type": "relation",
        "relation": "mt1,User,updated_by"
    },
    {
        "type": "relation",
        "relation": "1tm,Persona,honorific_id"
    }
]